{
  "id": "animal-whale-24",
  "name": "Whale 24",
  "category": "Animals",
  "width": 24,
  "height": 24,
  "palette": {
    "A": "#90caf9",
    "B": "#64b5f6"
  },
  "pixelGrid": [
    "........AAAAAAAA........",
    ".......AAAAAAAAAA.......",
    "......AAAAAAAAAAAA......",
    "......AAAAA....AAA......",
    "......AAAAAAAAAAAA......",
    ".......AAAAAAAAAA.......",
    "........AAAAAAAA........",
    ".........AAAAAA.........",
    "..........AAAA..........",
    "...........AA...........",
    "........................",
    "........................",
    "........................",
    "........................",
    "........................",
    "........................",
    "........................",
    "........................",
    "........................",
    "........................",
    "........................",
    "........................",
    "........................",
    "........................"
  ]
}
